ttn_cli/__init__.py
ttn_cli/cli.py
ttn_cli/shell_control.py
ttn_cli/modules/__init__.py
ttn_cli/modules/cmd_git.py
ttn_cli/modules/cmd_network.py
ttn_cli/modules/cmd_test.py
ttn_cli/test/__init__.py
ttn_cli/utils/__init__.py
ttn_cli/utils/constants.py
ttn_cli/utils/helper.py
ttncli-0.0.8.dist-info/LICENSE
ttncli-0.0.8.dist-info/METADATA
ttncli-0.0.8.dist-info/WHEEL
ttncli-0.0.8.dist-info/entry_points.txt
ttncli-0.0.8.dist-info/top_level.txt
ttncli-0.0.8.dist-info/RECORD
