Metadata-Version: 2.1
Name: ttncli
Version: 0.0.8
Summary: Basic Command line utility
Home-page: https://github.com/vibhor-kukreja/ttn-cli
Author: BASICCLI
Author-email: vibhor.kukreja@tothenew.com
License: UNKNOWN
Platform: UNKNOWN
Classifier: Programming Language :: Python :: 3
Classifier: Operating System :: OS Independent
Requires-Python: >=3.6
Requires-Dist: Click (==7.1.0)
Requires-Dist: GitPython (==3.1.3)
